examples/App-js.py
examples/enhanced_admin_security.py
examples/example_flask_integration.py
flask_honeypot-0.1.1.dist-info/licenses/LICENSE
honeypot/__init__.py
honeypot/_version.py
honeypot/cli.py
honeypot/backend/__init__.py
honeypot/backend/app.py
honeypot/backend/helpers/__init__.py
honeypot/backend/helpers/db_utils.py
honeypot/backend/helpers/geoip_manager.py
honeypot/backend/helpers/proxy_detector.py
honeypot/backend/helpers/unhackable.py
honeypot/backend/middleware/__init__.py
honeypot/backend/middleware/csrf_protection.py
honeypot/backend/routes/__init__.py
honeypot/backend/routes/admin.py
honeypot/backend/routes/honeypot.py
honeypot/backend/routes/honeypot_pages.py
honeypot/backend/routes/honeypot_routes.py
honeypot/backend/templates/honeypot/admin-dashboard.html
honeypot/backend/templates/honeypot/admin-login.html
honeypot/backend/templates/honeypot/cloud-dashboard.html
honeypot/backend/templates/honeypot/cms-dashboard.html
honeypot/backend/templates/honeypot/cpanel-dashboard.html
honeypot/backend/templates/honeypot/database-dashboard.html
honeypot/backend/templates/honeypot/debug-console.html
honeypot/backend/templates/honeypot/devops-dashboard.html
honeypot/backend/templates/honeypot/ecommerce-dashboard.html
honeypot/backend/templates/honeypot/filesharing-dashboard.html
honeypot/backend/templates/honeypot/forum-dashboard.html
honeypot/backend/templates/honeypot/framework-dashboard.html
honeypot/backend/templates/honeypot/generic-login.html
honeypot/backend/templates/honeypot/generic-page.html
honeypot/backend/templates/honeypot/iot-dashboard.html
honeypot/backend/templates/honeypot/mail-dashboard.html
honeypot/backend/templates/honeypot/mobile-api.html
honeypot/backend/templates/honeypot/monitoring-dashboard.html
honeypot/backend/templates/honeypot/phpmyadmin-dashboard.html
honeypot/backend/templates/honeypot/remote-access-dashboard.html
honeypot/backend/templates/honeypot/shell.html
honeypot/backend/templates/honeypot/wp-dashboard.html
honeypot/backend/templates/redirection/step1.html
flask_honeypot-0.1.1.dist-info/METADATA
flask_honeypot-0.1.1.dist-info/WHEEL
flask_honeypot-0.1.1.dist-info/entry_points.txt
flask_honeypot-0.1.1.dist-info/top_level.txt
flask_honeypot-0.1.1.dist-info/RECORD
