Metadata-Version: 2.4
Name: flask-honeypot
Version: 0.1.1
Summary: A comprehensive honeypot framework with admin dashboard
Author-email: Carter <support@certgames.com>
License: MIT
Project-URL: Homepage, https://github.com/CarterPerez-dev/honeypot-framework
Project-URL: Repository, https://github.com/CarterPerez-dev/honeypot-framework
Keywords: flask,honeypot,security,react,admin
Classifier: Development Status :: 4 - Beta
Classifier: Intended Audience :: Information Technology
Classifier: License :: OSI Approved :: MIT License
Classifier: Programming Language :: Python :: 3
Classifier: Programming Language :: Python :: 3.8
Classifier: Programming Language :: Python :: 3.9
Classifier: Programming Language :: Python :: 3.10
Classifier: Programming Language :: Python :: 3.11
Classifier: Topic :: Security
Requires-Python: >=3.8
License-File: LICENSE
Requires-Dist: flask>=2.2.0
Requires-Dist: flask-cors>=3.0.0
Requires-Dist: flask-session[redis]>=0.4.0
Requires-Dist: redis>=4.3.0
Requires-Dist: pymongo>=4.0.0
Requires-Dist: geoip2>=4.5.0
Requires-Dist: python-dotenv>=0.20.0
Requires-Dist: bcrypt>=4.0.0
Requires-Dist: user-agents>=2.2.0
Requires-Dist: python-socketio[client]>=5.7.0
Requires-Dist: gevent>=21.12.0
Requires-Dist: gunicorn>=20.1.0
Requires-Dist: werkzeug>=2.2.0
Requires-Dist: ipaddress>=1.0.0
Requires-Dist: requests>=2.27.0
Requires-Dist: click>=8.1.0
Provides-Extra: dev
Requires-Dist: pytest>=7.0.0; extra == "dev"
Requires-Dist: flake8>=5.0.0; extra == "dev"
Requires-Dist: black>=22.10.0; extra == "dev"
Requires-Dist: pytest-cov; extra == "dev"
Requires-Dist: mypy; extra == "dev"
Dynamic: license-file
